cs.srcset-1.1-py3.11-nspkg.pth
cs/srcset/__init__.py
cs/srcset/configure.zcml
cs/srcset/testing.py
cs/srcset/view.py
cs/srcset/locales/README.rst
cs/srcset/locales/__init__.py
cs/srcset/locales/cs.srcset.pot
cs/srcset/locales/update.py
cs/srcset/locales/update.sh
cs/srcset/locales/en/LC_MESSAGES/cs.srcset.mo
cs/srcset/locales/en/LC_MESSAGES/cs.srcset.po
cs/srcset/tests/__init__.py
cs/srcset/tests/test_view.py
cs.srcset-1.1.dist-info/LICENSE.GPL
cs.srcset-1.1.dist-info/LICENSE.rst
cs.srcset-1.1.dist-info/METADATA
cs.srcset-1.1.dist-info/WHEEL
cs.srcset-1.1.dist-info/entry_points.txt
cs.srcset-1.1.dist-info/namespace_packages.txt
cs.srcset-1.1.dist-info/top_level.txt
cs.srcset-1.1.dist-info/RECORD
